[
  {
    "id": 1,
    "name": "Company portfolio",
    "image": "https://i.ibb.co.com/PshXszP7/main-image.jpg",
    "description": "Developed a dynamic and user-friendly company portfolio website designed to streamline business operations. This platform includes essential features such as booking and appointment scheduling, lobby management for enhanced visitor experience, payroll information for employee transparency, and a seamless purchase system for smooth transactions. Built with a focus on efficiency, usability, and modern design, the website ensures an intuitive experience for both administrators and users.",
    "liveLink": "https://hellokompass.com/",
    "gitLink": "",
    "languageInfo": [],
    "allImages": [
      "https://i.ibb.co.com/cKjhH8CL/2025-01-31-19-05-00-Window.png",
      "https://i.ibb.co.com/4wKXNPQ1/2025-01-31-19-08-12-Window.png",
      "https://i.ibb.co.com/VcMR4GNP/2025-01-31-19-09-25-Window.png",
      "https://i.ibb.co.com/kgFL5TP8/2025-01-31-19-10-05-Window.png",
      "https://i.ibb.co.com/BHyWcc9W/2025-01-31-19-10-47.png",
      "https://i.ibb.co.com/KpczPZJ6/2025-01-31-19-11-10-Window.png",
      "https://i.ibb.co.com/tpBLK0R3/2025-01-31-19-11-58-Window.png",
      "https://i.ibb.co.com/kgJRG556/2025-01-31-19-12-20-Window.png",
      "https://i.ibb.co.com/BHz8Zb9h/2025-01-31-19-12-44-Window.png",
      "https://i.ibb.co.com/FbByhSDg/2025-01-31-19-13-20-Window.png",
      "https://i.ibb.co.com/5XH10PQh/2025-01-31-19-13-54.png",
      "https://i.ibb.co.com/4w2Ps3M2/2025-01-31-19-14-27-Window.png"
    ]
  },

  {
    "id": 2,
    "name": "Around the World in Eighty Days",
    "author": "Jules Verne"
  },

  { "id": 3, "name": "David Copperfield", "author": "Charles Dickens" },

  { "id": 4, "name": "The Adventures of Tom Sawyer", "author": "Mark Twain" },
  {
    "id": 5,
    "name": "Harry Potter and The Philosophers Stone",
    "author": "J.K. Rowley"
  }
]
